[
    {
        "sgg_cd": "530",
        "sgg_nm": "부여군",
        "corp_cnt": 17
    },
    {
        "sgg_cd": "030",
        "sgg_nm": "용산구",
        "corp_cnt": 187
    },
    {
        "sgg_cd": "051",
        "sgg_nm": "부천시 원미구",
        "corp_cnt": 250
    },
    {
        "sgg_cd": "530",
        "sgg_nm": "옥천군",
        "corp_cnt": 18
    },
    {
        "sgg_cd": "550",
        "sgg_nm": "고흥군",
        "corp_cnt": 18
    },
    {
        "sgg_cd": "030",
        "sgg_nm": "보령시",
        "corp_cnt": 49
    },
    {
        "sgg_cd": "021",
        "sgg_nm": "성남시 수정구",
        "corp_cnt": 138
    },
    {
        "sgg_cd": "040",
        "sgg_nm": "영도구",
        "corp_cnt": 49
    },
    {
        "sgg_cd": "012",
        "sgg_nm": "수원시 권선구",
        "corp_cnt": 154
    },
    {
        "sgg_cd": "040",
        "sgg_nm": "남구",
        "corp_cnt": 86
    },
    {
        "sgg_cd": "044",
        "sgg_nm": "청주시 청원구",
        "corp_cnt": 111
    },
    {
        "sgg_cd": "160",
        "sgg_nm": "강서구",
        "corp_cnt": 313
    },
    {
        "sgg_cd": "100",
        "sgg_nm": "양산시",
        "corp_cnt": 216
    },
    {
        "sgg_cd": "510",
        "sgg_nm": "강화군",
        "corp_cnt": 29
    },
    {
        "sgg_cd": "200",
        "sgg_nm": "파주시",
        "corp_cnt": 269
    },
    {
        "sgg_cd": "020",
        "sgg_nm": "중구",
        "corp_cnt": 173
    },
    {
        "sgg_cd": "020",
        "sgg_nm": "공주시",
        "corp_cnt": 45
    },
    {
        "sgg_cd": "014",
        "sgg_nm": "수원시 영통구",
        "corp_cnt": 241
    },
    {
        "sgg_cd": "080",
        "sgg_nm": "상주시",
        "corp_cnt": 41
    },
    {
        "sgg_cd": "020",
        "sgg_nm": "동구",
        "corp_cnt": 17
    },
    {
        "sgg_cd": "050",
        "sgg_nm": "서산시",
        "corp_cnt": 96
    },
    {
        "sgg_cd": "620",
        "sgg_nm": "무안군",
        "corp_cnt": 48
    },
    {
        "sgg_cd": "010",
        "sgg_nm": "중구",
        "corp_cnt": 44
    },
    {
        "sgg_cd": "510",
        "sgg_nm": "완주군",
        "corp_cnt": 43
    },
    {
        "sgg_cd": "050",
        "sgg_nm": "구미시",
        "corp_cnt": 228
    },
    {
        "sgg_cd": "150",
        "sgg_nm": "양천구",
        "corp_cnt": 182
    },
    {
        "sgg_cd": "020",
        "sgg_nm": "경주시",
        "corp_cnt": 142
    },
    {
        "sgg_cd": "050",
        "sgg_nm": "통영시",
        "corp_cnt": 59
    },
    {
        "sgg_cd": "040",
        "sgg_nm": "나주시",
        "corp_cnt": 59
    },
    {
        "sgg_cd": "030",
        "sgg_nm": "강릉시",
        "corp_cnt": 147
    },
    {
        "sgg_cd": "570",
        "sgg_nm": "고령군",
        "corp_cnt": 9
    },
    {
        "sgg_cd": "550",
        "sgg_nm": "영덕군",
        "corp_cnt": 19
    },
    {
        "sgg_cd": "550",
        "sgg_nm": "정선군",
        "corp_cnt": 15
    },
    {
        "sgg_cd": "020",
        "sgg_nm": "충주시",
        "corp_cnt": 117
    },
    {
        "sgg_cd": "140",
        "sgg_nm": "오산시",
        "corp_cnt": 112
    },
    {
        "sgg_cd": "030",
        "sgg_nm": "서구",
        "corp_cnt": 57
    },
    {
        "sgg_cd": "580",
        "sgg_nm": "성주군",
        "corp_cnt": 11
    },
    {
        "sgg_cd": "150",
        "sgg_nm": "시흥시",
        "corp_cnt": 278
    },
    {
        "sgg_cd": "560",
        "sgg_nm": "철원군",
        "corp_cnt": 31
    },
    {
        "sgg_cd": "070",
        "sgg_nm": "남구",
        "corp_cnt": 137
    },
    {
        "sgg_cd": "070",
        "sgg_nm": "달서구",
        "corp_cnt": 258
    },
    {
        "sgg_cd": "630",
        "sgg_nm": "함평군",
        "corp_cnt": 5
    },
    {
        "sgg_cd": "030",
        "sgg_nm": "동구",
        "corp_cnt": 42
    },
    {
        "sgg_cd": "050",
        "sgg_nm": "남원시",
        "corp_cnt": 30
    },
    {
        "sgg_cd": "230",
        "sgg_nm": "김포시",
        "corp_cnt": 239
    },
    {
        "sgg_cd": "570",
        "sgg_nm": "음성군",
        "corp_cnt": 51
    },
    {
        "sgg_cd": "030",
        "sgg_nm": "익산시",
        "corp_cnt": 128
    },
    {
        "sgg_cd": "180",
        "sgg_nm": "하남시",
        "corp_cnt": 162
    },
    {
        "sgg_cd": "590",
        "sgg_nm": "강진군",
        "corp_cnt": 8
    },
    {
        "sgg_cd": "060",
        "sgg_nm": "논산시",
        "corp_cnt": 47
    },
    {
        "sgg_cd": "050",
        "sgg_nm": "대덕구",
        "corp_cnt": 78
    },
    {
        "sgg_cd": "130",
        "sgg_nm": "연제구",
        "corp_cnt": 104
    },
    {
        "sgg_cd": "560",
        "sgg_nm": "청도군",
        "corp_cnt": 16
    },
    {
        "sgg_cd": "110",
        "sgg_nm": "금정구",
        "corp_cnt": 135
    },
    {
        "sgg_cd": "030",
        "sgg_nm": "김천시",
        "corp_cnt": 52
    },
    {
        "sgg_cd": "530",
        "sgg_nm": "영월군",
        "corp_cnt": 11
    },
    {
        "sgg_cd": "590",
        "sgg_nm": "칠곡군",
        "corp_cnt": 44
    },
    {
        "sgg_cd": "010",
        "sgg_nm": "춘천시",
        "corp_cnt": 197
    },
    {
        "sgg_cd": "060",
        "sgg_nm": "속초시",
        "corp_cnt": 57
    },
    {
        "sgg_cd": "012",
        "sgg_nm": "천안시 서북구",
        "corp_cnt": 264
    },
    {
        "sgg_cd": "120",
        "sgg_nm": "은평구",
        "corp_cnt": 183
    },
    {
        "sgg_cd": "020",
        "sgg_nm": "군산시",
        "corp_cnt": 108
    },
    {
        "sgg_cd": "580",
        "sgg_nm": "부안군",
        "corp_cnt": 19
    },
    {
        "sgg_cd": "200",
        "sgg_nm": "동작구",
        "corp_cnt": 184
    },
    {
        "sgg_cd": "240",
        "sgg_nm": "송파구",
        "corp_cnt": 375
    },
    {
        "sgg_cd": "130",
        "sgg_nm": "남양주시",
        "corp_cnt": 338
    },
    {
        "sgg_cd": "610",
        "sgg_nm": "봉화군",
        "corp_cnt": 7
    },
    {
        "sgg_cd": "220",
        "sgg_nm": "안성시",
        "corp_cnt": 102
    },
    {
        "sgg_cd": "113",
        "sgg_nm": "창원시 마산합포구",
        "corp_cnt": 86
    },
    {
        "sgg_cd": "101",
        "sgg_nm": "고양시 덕양구",
        "corp_cnt": 234
    },
    {
        "sgg_cd": "540",
        "sgg_nm": "영동군",
        "corp_cnt": 17
    },
    {
        "sgg_cd": "110",
        "sgg_nm": "노원구",
        "corp_cnt": 199
    },
    {
        "sgg_cd": "010",
        "sgg_nm": "중구",
        "corp_cnt": 113
    },
    {
        "sgg_cd": "250",
        "sgg_nm": "광주시",
        "corp_cnt": 163
    },
    {
        "sgg_cd": "110",
        "sgg_nm": "과천시",
        "corp_cnt": 23
    },
    {
        "sgg_cd": "010",
        "sgg_nm": "중구",
        "corp_cnt": 98
    },
    {
        "sgg_cd": "050",
        "sgg_nm": "남동구",
        "corp_cnt": 251
    },
    {
        "sgg_cd": "550",
        "sgg_nm": "연천군",
        "corp_cnt": 26
    },
    {
        "sgg_cd": "580",
        "sgg_nm": "양구군",
        "corp_cnt": 17
    },
    {
        "sgg_cd": "050",
        "sgg_nm": "광산구",
        "corp_cnt": 216
    },
    {
        "sgg_cd": "510",
        "sgg_nm": "금산군",
        "corp_cnt": 18
    },
    {
        "sgg_cd": "060",
        "sgg_nm": "동대문구",
        "corp_cnt": 187
    },
    {
        "sgg_cd": "260",
        "sgg_nm": "양주시",
        "corp_cnt": 111
    },
    {
        "sgg_cd": "042",
        "sgg_nm": "청주시 서원구",
        "corp_cnt": 85
    },
    {
        "sgg_cd": "650",
        "sgg_nm": "장성군",
        "corp_cnt": 14
    },
    {
        "sgg_cd": "580",
        "sgg_nm": "함양군",
        "corp_cnt": 15
    },
    {
        "sgg_cd": "111",
        "sgg_nm": "창원시 의창구",
        "corp_cnt": 125
    },
    {
        "sgg_cd": "100",
        "sgg_nm": "사하구",
        "corp_cnt": 146
    },
    {
        "sgg_cd": "550",
        "sgg_nm": "남해군",
        "corp_cnt": 22
    },
    {
        "sgg_cd": "510",
        "sgg_nm": "기장군",
        "corp_cnt": 123
    },
    {
        "sgg_cd": "053",
        "sgg_nm": "부천시 오정구",
        "corp_cnt": 59
    },
    {
        "sgg_cd": "050",
        "sgg_nm": "북구",
        "corp_cnt": 227
    },
    {
        "sgg_cd": "660",
        "sgg_nm": "완도군",
        "corp_cnt": 18
    },
    {
        "sgg_cd": "520",
        "sgg_nm": "군위군",
        "corp_cnt": 6
    },
    {
        "sgg_cd": "060",
        "sgg_nm": "동래구",
        "corp_cnt": 125
    },
    {
        "sgg_cd": "104",
        "sgg_nm": "고양시 일산서구",
        "corp_cnt": 127
    },
    {
        "sgg_cd": "070",
        "sgg_nm": "평택시",
        "corp_cnt": 342
    },
    {
        "sgg_cd": "040",
        "sgg_nm": "성동구",
        "corp_cnt": 176
    },
    {
        "sgg_cd": "112",
        "sgg_nm": "창원시 성산구",
        "corp_cnt": 143
    },
    {
        "sgg_cd": "010",
        "sgg_nm": "동구",
        "corp_cnt": 119
    },
    {
        "sgg_cd": "630",
        "sgg_nm": "울릉군",
        "corp_cnt": 5
    },
    {
        "sgg_cd": "250",
        "sgg_nm": "강동구",
        "corp_cnt": 204
    },
    {
        "sgg_cd": "520",
        "sgg_nm": "보은군",
        "corp_cnt": 10
    },
    {
        "sgg_cd": "540",
        "sgg_nm": "고성군",
        "corp_cnt": 15
    },
    {
        "sgg_cd": "023",
        "sgg_nm": "성남시 분당구",
        "corp_cnt": 292
    },
    {
        "sgg_cd": "080",
        "sgg_nm": "북구",
        "corp_cnt": 115
    },
    {
        "sgg_cd": "550",
        "sgg_nm": "임실군",
        "corp_cnt": 9
    },
    {
        "sgg_cd": "060",
        "sgg_nm": "광명시",
        "corp_cnt": 122
    },
    {
        "sgg_cd": "160",
        "sgg_nm": "군포시",
        "corp_cnt": 107
    },
    {
        "sgg_cd": "020",
        "sgg_nm": "서구",
        "corp_cnt": 150
    },
    {
        "sgg_cd": "550",
        "sgg_nm": "진천군",
        "corp_cnt": 47
    },
    {
        "sgg_cd": "680",
        "sgg_nm": "신안군",
        "corp_cnt": 1
    },
    {
        "sgg_cd": "100",
        "sgg_nm": "경산시",
        "corp_cnt": 166
    },
    {
        "sgg_cd": "610",
        "sgg_nm": "양양군",
        "corp_cnt": 29
    },
    {
        "sgg_cd": "010",
        "sgg_nm": "목포시",
        "corp_cnt": 112
    },
    {
        "sgg_cd": "013",
        "sgg_nm": "수원시 팔달구",
        "corp_cnt": 120
    },
    {
        "sgg_cd": "600",
        "sgg_nm": "예천군",
        "corp_cnt": 21
    },
    {
        "sgg_cd": "115",
        "sgg_nm": "창원시 진해구",
        "corp_cnt": 105
    },
    {
        "sgg_cd": "220",
        "sgg_nm": "서초구",
        "corp_cnt": 230
    },
    {
        "sgg_cd": "042",
        "sgg_nm": "안양시 동안구",
        "corp_cnt": 144
    },
    {
        "sgg_cd": "011",
        "sgg_nm": "수원시 장안구",
        "corp_cnt": 120
    },
    {
        "sgg_cd": "090",
        "sgg_nm": "문경시",
        "corp_cnt": 23
    },
    {
        "sgg_cd": "030",
        "sgg_nm": "의정부시",
        "corp_cnt": 226
    },
    {
        "sgg_cd": "560",
        "sgg_nm": "보성군",
        "corp_cnt": 11
    },
    {
        "sgg_cd": "020",
        "sgg_nm": "원주시",
        "corp_cnt": 219
    },
    {
        "sgg_cd": "020",
        "sgg_nm": "여수시",
        "corp_cnt": 145
    },
    {
        "sgg_cd": "191",
        "sgg_nm": "용인시 처인구",
        "corp_cnt": 121
    },
    {
        "sgg_cd": "010",
        "sgg_nm": "세종시",
        "corp_cnt": 217
    },
    {
        "sgg_cd": "520",
        "sgg_nm": "횡성군",
        "corp_cnt": 19
    },
    {
        "sgg_cd": "570",
        "sgg_nm": "산청군",
        "corp_cnt": 13
    },
    {
        "sgg_cd": "100",
        "sgg_nm": "도봉구",
        "corp_cnt": 108
    },
    {
        "sgg_cd": "140",
        "sgg_nm": "수영구",
        "corp_cnt": 106
    },
    {
        "sgg_cd": "040",
        "sgg_nm": "유성구",
        "corp_cnt": 251
    },
    {
        "sgg_cd": "620",
        "sgg_nm": "울진군",
        "corp_cnt": 23
    },
    {
        "sgg_cd": "530",
        "sgg_nm": "구례군",
        "corp_cnt": 10
    },
    {
        "sgg_cd": "193",
        "sgg_nm": "용인시 수지구",
        "corp_cnt": 145
    },
    {
        "sgg_cd": "510",
        "sgg_nm": "홍천군",
        "corp_cnt": 34
    },
    {
        "sgg_cd": "011",
        "sgg_nm": "전주시 완산구",
        "corp_cnt": 203
    },
    {
        "sgg_cd": "600",
        "sgg_nm": "합천군",
        "corp_cnt": 11
    },
    {
        "sgg_cd": "090",
        "sgg_nm": "거제시",
        "corp_cnt": 136
    },
    {
        "sgg_cd": "140",
        "sgg_nm": "마포구",
        "corp_cnt": 349
    },
    {
        "sgg_cd": "670",
        "sgg_nm": "진도군",
        "corp_cnt": 12
    },
    {
        "sgg_cd": "540",
        "sgg_nm": "평창군",
        "corp_cnt": 32
    },
    {
        "sgg_cd": "030",
        "sgg_nm": "진주시",
        "corp_cnt": 203
    },
    {
        "sgg_cd": "080",
        "sgg_nm": "서구",
        "corp_cnt": 250
    },
    {
        "sgg_cd": "180",
        "sgg_nm": "금천구",
        "corp_cnt": 123
    },
    {
        "sgg_cd": "010",
        "sgg_nm": "동구",
        "corp_cnt": 87
    },
    {
        "sgg_cd": "060",
        "sgg_nm": "사천시",
        "corp_cnt": 50
    },
    {
        "sgg_cd": "570",
        "sgg_nm": "화순군",
        "corp_cnt": 25
    },
    {
        "sgg_cd": "091",
        "sgg_nm": "안산시 상록구",
        "corp_cnt": 144
    },
    {
        "sgg_cd": "210",
        "sgg_nm": "이천시",
        "corp_cnt": 127
    },
    {
        "sgg_cd": "590",
        "sgg_nm": "인제군",
        "corp_cnt": 19
    },
    {
        "sgg_cd": "520",
        "sgg_nm": "곡성군",
        "corp_cnt": 7
    },
    {
        "sgg_cd": "070",
        "sgg_nm": "김해시",
        "corp_cnt": 298
    },
    {
        "sgg_cd": "210",
        "sgg_nm": "관악구",
        "corp_cnt": 242
    },
    {
        "sgg_cd": "192",
        "sgg_nm": "용인시 기흥구",
        "corp_cnt": 193
    },
    {
        "sgg_cd": "520",
        "sgg_nm": "의성군",
        "corp_cnt": 15
    },
    {
        "sgg_cd": "170",
        "sgg_nm": "의왕시",
        "corp_cnt": 60
    },
    {
        "sgg_cd": "520",
        "sgg_nm": "진안군",
        "corp_cnt": 5
    },
    {
        "sgg_cd": "020",
        "sgg_nm": "동구",
        "corp_cnt": 150
    },
    {
        "sgg_cd": "040",
        "sgg_nm": "안동시",
        "corp_cnt": 74
    },
    {
        "sgg_cd": "040",
        "sgg_nm": "정읍시",
        "corp_cnt": 44
    },
    {
        "sgg_cd": "080",
        "sgg_nm": "당진시",
        "corp_cnt": 77
    },
    {
        "sgg_cd": "570",
        "sgg_nm": "가평군",
        "corp_cnt": 45
    },
    {
        "sgg_cd": "120",
        "sgg_nm": "강서구",
        "corp_cnt": 89
    },
    {
        "sgg_cd": "560",
        "sgg_nm": "괴산군",
        "corp_cnt": 10
    },
    {
        "sgg_cd": "530",
        "sgg_nm": "무주군",
        "corp_cnt": 11
    },
    {
        "sgg_cd": "040",
        "sgg_nm": "북구",
        "corp_cnt": 228
    },
    {
        "sgg_cd": "030",
        "sgg_nm": "제천시",
        "corp_cnt": 66
    },
    {
        "sgg_cd": "040",
        "sgg_nm": "아산시",
        "corp_cnt": 179
    },
    {
        "sgg_cd": "540",
        "sgg_nm": "장수군",
        "corp_cnt": 7
    },
    {
        "sgg_cd": "011",
        "sgg_nm": "천안시 동남구",
        "corp_cnt": 141
    },
    {
        "sgg_cd": "530",
        "sgg_nm": "창녕군",
        "corp_cnt": 27
    },
    {
        "sgg_cd": "030",
        "sgg_nm": "동구",
        "corp_cnt": 76
    },
    {
        "sgg_cd": "020",
        "sgg_nm": "남구",
        "corp_cnt": 211
    },
    {
        "sgg_cd": "510",
        "sgg_nm": "의령군",
        "corp_cnt": 6
    },
    {
        "sgg_cd": "070",
        "sgg_nm": "계룡시",
        "corp_cnt": 26
    },
    {
        "sgg_cd": "114",
        "sgg_nm": "창원시 마산회원구",
        "corp_cnt": 82
    },
    {
        "sgg_cd": "560",
        "sgg_nm": "하동군",
        "corp_cnt": 14
    },
    {
        "sgg_cd": "012",
        "sgg_nm": "포항시 북구",
        "corp_cnt": 131
    },
    {
        "sgg_cd": "090",
        "sgg_nm": "강북구",
        "corp_cnt": 140
    },
    {
        "sgg_cd": "530",
        "sgg_nm": "청송군",
        "corp_cnt": 5
    },
    {
        "sgg_cd": "011",
        "sgg_nm": "포항시 남구",
        "corp_cnt": 130
    },
    {
        "sgg_cd": "041",
        "sgg_nm": "청주시 상당구",
        "corp_cnt": 95
    },
    {
        "sgg_cd": "600",
        "sgg_nm": "고성군",
        "corp_cnt": 12
    },
    {
        "sgg_cd": "040",
        "sgg_nm": "동해시",
        "corp_cnt": 48
    },
    {
        "sgg_cd": "080",
        "sgg_nm": "동두천시",
        "corp_cnt": 56
    },
    {
        "sgg_cd": "190",
        "sgg_nm": "영등포구",
        "corp_cnt": 237
    },
    {
        "sgg_cd": "230",
        "sgg_nm": "강남구",
        "corp_cnt": 495
    },
    {
        "sgg_cd": "022",
        "sgg_nm": "성남시 중원구",
        "corp_cnt": 77
    },
    {
        "sgg_cd": "092",
        "sgg_nm": "안산시 단원구",
        "corp_cnt": 166
    },
    {
        "sgg_cd": "580",
        "sgg_nm": "장흥군",
        "corp_cnt": 8
    },
    {
        "sgg_cd": "060",
        "sgg_nm": "부평구",
        "corp_cnt": 235
    },
    {
        "sgg_cd": "520",
        "sgg_nm": "옹진군",
        "corp_cnt": 8
    },
    {
        "sgg_cd": "580",
        "sgg_nm": "양평군",
        "corp_cnt": 34
    },
    {
        "sgg_cd": "080",
        "sgg_nm": "성북구",
        "corp_cnt": 195
    },
    {
        "sgg_cd": "040",
        "sgg_nm": "북구",
        "corp_cnt": 123
    },
    {
        "sgg_cd": "060",
        "sgg_nm": "광양시",
        "corp_cnt": 80
    },
    {
        "sgg_cd": "020",
        "sgg_nm": "서귀포시",
        "corp_cnt": 125
    },
    {
        "sgg_cd": "580",
        "sgg_nm": "단양군",
        "corp_cnt": 11
    },
    {
        "sgg_cd": "550",
        "sgg_nm": "청양군",
        "corp_cnt": 9
    },
    {
        "sgg_cd": "070",
        "sgg_nm": "삼척시",
        "corp_cnt": 37
    },
    {
        "sgg_cd": "130",
        "sgg_nm": "서대문구",
        "corp_cnt": 189
    },
    {
        "sgg_cd": "510",
        "sgg_nm": "울주군",
        "corp_cnt": 90
    },
    {
        "sgg_cd": "041",
        "sgg_nm": "안양시 만안구",
        "corp_cnt": 121
    },
    {
        "sgg_cd": "060",
        "sgg_nm": "김제시",
        "corp_cnt": 24
    },
    {
        "sgg_cd": "040",
        "sgg_nm": "연수구",
        "corp_cnt": 217
    },
    {
        "sgg_cd": "060",
        "sgg_nm": "수성구",
        "corp_cnt": 239
    },
    {
        "sgg_cd": "150",
        "sgg_nm": "사상구",
        "corp_cnt": 101
    },
    {
        "sgg_cd": "103",
        "sgg_nm": "고양시 일산동구",
        "corp_cnt": 179
    },
    {
        "sgg_cd": "050",
        "sgg_nm": "광진구",
        "corp_cnt": 188
    },
    {
        "sgg_cd": "010",
        "sgg_nm": "중구",
        "corp_cnt": 126
    },
    {
        "sgg_cd": "010",
        "sgg_nm": "제주시",
        "corp_cnt": 376
    },
    {
        "sgg_cd": "090",
        "sgg_nm": "해운대구",
        "corp_cnt": 222
    },
    {
        "sgg_cd": "070",
        "sgg_nm": "중랑구",
        "corp_cnt": 135
    },
    {
        "sgg_cd": "030",
        "sgg_nm": "남구",
        "corp_cnt": 118
    },
    {
        "sgg_cd": "030",
        "sgg_nm": "순천시",
        "corp_cnt": 135
    },
    {
        "sgg_cd": "580",
        "sgg_nm": "태안군",
        "corp_cnt": 28
    },
    {
        "sgg_cd": "590",
        "sgg_nm": "증평군",
        "corp_cnt": 23
    },
    {
        "sgg_cd": "540",
        "sgg_nm": "영양군",
        "corp_cnt": 4
    },
    {
        "sgg_cd": "570",
        "sgg_nm": "화천군",
        "corp_cnt": 24
    },
    {
        "sgg_cd": "052",
        "sgg_nm": "부천시 소사구",
        "corp_cnt": 86
    },
    {
        "sgg_cd": "080",
        "sgg_nm": "밀양시",
        "corp_cnt": 33
    },
    {
        "sgg_cd": "570",
        "sgg_nm": "고창군",
        "corp_cnt": 12
    },
    {
        "sgg_cd": "120",
        "sgg_nm": "구리시",
        "corp_cnt": 98
    },
    {
        "sgg_cd": "010",
        "sgg_nm": "종로구",
        "corp_cnt": 179
    },
    {
        "sgg_cd": "050",
        "sgg_nm": "태백시",
        "corp_cnt": 16
    },
    {
        "sgg_cd": "640",
        "sgg_nm": "영광군",
        "corp_cnt": 19
    },
    {
        "sgg_cd": "540",
        "sgg_nm": "서천군",
        "corp_cnt": 17
    },
    {
        "sgg_cd": "520",
        "sgg_nm": "함안군",
        "corp_cnt": 27
    },
    {
        "sgg_cd": "020",
        "sgg_nm": "서구",
        "corp_cnt": 51
    },
    {
        "sgg_cd": "510",
        "sgg_nm": "담양군",
        "corp_cnt": 12
    },
    {
        "sgg_cd": "570",
        "sgg_nm": "예산군",
        "corp_cnt": 34
    },
    {
        "sgg_cd": "280",
        "sgg_nm": "여주시",
        "corp_cnt": 50
    },
    {
        "sgg_cd": "560",
        "sgg_nm": "홍성군",
        "corp_cnt": 50
    },
    {
        "sgg_cd": "043",
        "sgg_nm": "청주시 흥덕구",
        "corp_cnt": 174
    },
    {
        "sgg_cd": "090",
        "sgg_nm": "미추홀구",
        "corp_cnt": 186
    },
    {
        "sgg_cd": "170",
        "sgg_nm": "구로구",
        "corp_cnt": 175
    },
    {
        "sgg_cd": "270",
        "sgg_nm": "포천시",
        "corp_cnt": 77
    },
    {
        "sgg_cd": "020",
        "sgg_nm": "중구",
        "corp_cnt": 104
    },
    {
        "sgg_cd": "012",
        "sgg_nm": "전주시 덕진구",
        "corp_cnt": 183
    },
    {
        "sgg_cd": "590",
        "sgg_nm": "거창군",
        "corp_cnt": 23
    },
    {
        "sgg_cd": "600",
        "sgg_nm": "해남군",
        "corp_cnt": 20
    },
    {
        "sgg_cd": "070",
        "sgg_nm": "영천시",
        "corp_cnt": 30
    },
    {
        "sgg_cd": "060",
        "sgg_nm": "영주시",
        "corp_cnt": 42
    },
    {
        "sgg_cd": "030",
        "sgg_nm": "서구",
        "corp_cnt": 289
    },
    {
        "sgg_cd": "510",
        "sgg_nm": "달성군",
        "corp_cnt": 120
    },
    {
        "sgg_cd": "240",
        "sgg_nm": "화성시",
        "corp_cnt": 471
    },
    {
        "sgg_cd": "610",
        "sgg_nm": "영암군",
        "corp_cnt": 22
    },
    {
        "sgg_cd": "050",
        "sgg_nm": "부산진구",
        "corp_cnt": 214
    },
    {
        "sgg_cd": "560",
        "sgg_nm": "순창군",
        "corp_cnt": 7
    },
    {
        "sgg_cd": "070",
        "sgg_nm": "계양구",
        "corp_cnt": 119
    }
]